tarvis/btb/__init__.py
tarvis/btb/basictradingbot.py
tarvis/btb/btbs.py
tarvis/btb/exchangeaccount.py
tarvis_btb-0.9.6.dist-info/LICENSE.txt
tarvis_btb-0.9.6.dist-info/METADATA
tarvis_btb-0.9.6.dist-info/WHEEL
tarvis_btb-0.9.6.dist-info/top_level.txt
tarvis_btb-0.9.6.dist-info/RECORD
